fcecodec.cp312-win32.pyd
fcecodec-1.11.dist-info/LICENSE
fcecodec-1.11.dist-info/METADATA
fcecodec-1.11.dist-info/WHEEL
fcecodec-1.11.dist-info/top_level.txt
fcecodec-1.11.dist-info/RECORD
