Metadata-Version: 2.1
Name: fcecodec
Version: 1.11
Summary: FCE decoder/encoder
Home-page: https://github.com/bfut/fcecodec
Author: Benjamin Futasz
License: GPLv2+
Requires-Python: >=3.10
License-File: LICENSE
